authflow/__init__.py
authflow/client.py
authflow_sdk-1.0.0.dist-info/METADATA
authflow_sdk-1.0.0.dist-info/WHEEL
authflow_sdk-1.0.0.dist-info/top_level.txt
authflow_sdk-1.0.0.dist-info/RECORD
