Metadata-Version: 2.4
Name: authflow-sdk
Version: 1.0.0
Summary: Official AuthFlow SDK for Python
Home-page: https://authflow.com
Author: AuthFlow
Author-email: support@authflow.com
Keywords: auth,authentication,authflow,oauth,sdk
Classifier: Programming Language :: Python :: 3
Classifier: License :: OSI Approved :: MIT License
Classifier: Operating System :: OS Independent
Requires-Python: >=3.6
Requires-Dist: requests>=2.25.0
Dynamic: author
Dynamic: author-email
Dynamic: classifier
Dynamic: home-page
Dynamic: keywords
Dynamic: requires-dist
Dynamic: requires-python
Dynamic: summary
